mcp_nefino/__init__.py
mcp_nefino/client.py
mcp_nefino/config.py
mcp_nefino/enums.py
mcp_nefino/server.py
mcp_nefino/task_manager.py
mcp_nefino/validation.py
mseep_mcp_nefino-0.1.7.dist-info/METADATA
mseep_mcp_nefino-0.1.7.dist-info/WHEEL
mseep_mcp_nefino-0.1.7.dist-info/entry_points.txt
mseep_mcp_nefino-0.1.7.dist-info/licenses/LICENSE
mseep_mcp_nefino-0.1.7.dist-info/RECORD
