Metadata-Version: 2.4
Name: mseep-mcp-nefino
Version: 0.1.7
Summary: MCP server for accessing Nefino renewable energy news API
Author-email: mseep <support@skydeck.ai>
Maintainer-email: mseep <support@skydeck.ai>
License-Expression: Apache-2.0
License-File: LICENSE
Requires-Python: >=3.10
Requires-Dist: aiohttp
Requires-Dist: fastapi
Requires-Dist: mcp>=1.3.0
Requires-Dist: pydantic
Requires-Dist: python-jose
Requires-Dist: requests
